odoo/addons/hr_contract_renew/README.rst
odoo/addons/hr_contract_renew/__init__.py
odoo/addons/hr_contract_renew/__manifest__.py
odoo/addons/hr_contract_renew/i18n/hr_contract_renew.pot
odoo/addons/hr_contract_renew/i18n/it.po
odoo/addons/hr_contract_renew/readme/DESCRIPTION.md
odoo/addons/hr_contract_renew/readme/USAGE.md
odoo/addons/hr_contract_renew/security/ir.model.access.csv
odoo/addons/hr_contract_renew/static/description/icon.png
odoo/addons/hr_contract_renew/static/description/index.html
odoo/addons/hr_contract_renew/tests/__init__.py
odoo/addons/hr_contract_renew/tests/test_hr_contract_renew.py
odoo/addons/hr_contract_renew/views/hr_contract_view.xml
odoo/addons/hr_contract_renew/wizards/__init__.py
odoo/addons/hr_contract_renew/wizards/hr_contract_renew_wizard.py
odoo/addons/hr_contract_renew/wizards/hr_contract_renew_wizard.xml
odoo_addon_hr_contract_renew-18.0.1.0.0.4.dist-info/METADATA
odoo_addon_hr_contract_renew-18.0.1.0.0.4.dist-info/WHEEL
odoo_addon_hr_contract_renew-18.0.1.0.0.4.dist-info/top_level.txt
odoo_addon_hr_contract_renew-18.0.1.0.0.4.dist-info/RECORD
